{"followLerp":0.04,"defaultCamZoom":0.9,"sprites":[{"pos":[400,130],"src":"","shader":null,"beatTween":null,"alpha":1,"scrollFactor":[0.95,0.95],"antialiasing":true,"name":"Girlfriend","animation":null,"type":"GF","scale":1},{"pos":[-1295,-1032],"src":"stages/bars/fazbars","shader":"","beatTween":{"x":0,"y":0,"ease":"linear"},"alpha":1,"scrollFactor":[1,1],"antialiasing":false,"name":"fazbars","animation":null,"type":"Bitmap","scale":4},{"pos":[-265,-607],"src":"","shader":"","beatTween":{"x":0,"y":0,"ease":"linear"},"alpha":1,"scrollFactor":[1,1],"antialiasing":true,"name":"Dad","animation":null,"type":"Dad","scale":1},{"pos":[736,266],"src":"","shader":"","beatTween":{"x":0,"y":0,"ease":"linear"},"alpha":1,"scrollFactor":[1,1],"antialiasing":true,"name":"Boyfriend","animation":null,"type":"BF","scale":1}],"gfOffset":[0,0],"dadOffset":[-35,-217],"bfOffset":[-34,-184]}